dist
docs
knockpy
proftest
test
