Metadata-Version: 2.4
Name: knockpy
Version: 1.3.4
Summary: Knockoffs for variable selection
Author-email: Asher Spector <amspector100@gmail.com>
License-Expression: MIT
Project-URL: Documentation, https://amspector100.github.io/knockpy
Project-URL: Repository, https://github.com/amspector100/knockpy
Project-URL: Issues, https://github.com/amspector100/knockpy/issues
Classifier: Programming Language :: Python :: 3
Classifier: Operating System :: OS Independent
Requires-Python: >=3.9
License-File: LICENSE.txt
Requires-Dist: jlc-choldate>=0.4
Requires-Dist: cvxpy>=1.0.25
Requires-Dist: networkx>=2.4
Requires-Dist: numpy>=2.0
Requires-Dist: scikit_learn>=0.22
Requires-Dist: scipy>=1.5.2
Requires-Dist: tqdm>=4.36.1
Provides-Extra: kpytorch
Requires-Dist: torch>=1.4.0; extra == "kpytorch"
Provides-Extra: fast
Requires-Dist: jlc-scikit-dsdp>=0.3; extra == "fast"
Provides-Extra: docs
Requires-Dist: sphinx; extra == "docs"
Requires-Dist: sphinx-rtd-theme; extra == "docs"
Dynamic: license-file
